swc_ephys/__init__.py
swc_ephys/command_line_interface.py
swc_ephys/configs/configs.py
swc_ephys/configs/default.yaml
swc_ephys/configs/test_pp_large_file.yaml
swc_ephys/configs/test_pp_small_file.yaml
swc_ephys/data_classes/base.py
swc_ephys/data_classes/preprocessing.py
swc_ephys/data_classes/sorting.py
swc_ephys/examples/example_full_pipeline.py
swc_ephys/examples/example_postprocess.py
swc_ephys/examples/example_sort.py
swc_ephys/examples/example_visualise.py
swc_ephys/examples/example_visualise_preprocessing_output.py
swc_ephys/pipeline/full_pipeline.py
swc_ephys/pipeline/load_data.py
swc_ephys/pipeline/postprocess.py
swc_ephys/pipeline/preprocess.py
swc_ephys/pipeline/sort.py
swc_ephys/pipeline/visualise.py
swc_ephys/pipeline/waveform_compare.py
swc_ephys/utils/custom_types.py
swc_ephys/utils/slurm.py
swc_ephys/utils/utils.py
swc_ephys-0.0.0.dist-info/LICENSE
swc_ephys-0.0.0.dist-info/METADATA
swc_ephys-0.0.0.dist-info/WHEEL
swc_ephys-0.0.0.dist-info/entry_points.txt
swc_ephys-0.0.0.dist-info/top_level.txt
swc_ephys-0.0.0.dist-info/RECORD
