Metadata-Version: 2.1
Name: swc-ephys
Version: 0.0.0
Summary: Manage extracellular electrophysiology analysis
Author-email: Joe Ziminski <joseph.j.ziminski@gmail.com>
License: BSD-3-Clause
Project-URL: homepage, https://github.com/JoeZiminski/swc_ephys
Project-URL: bug_tracker, https://github.com/JoeZiminski/swc_ephys/issues
Project-URL: documentation, https://github.com/JoeZiminski/swc_ephys
Project-URL: source_code, https://github.com/JoeZiminski/swc_ephys
Project-URL: user_support, https://github.com/JoeZiminski/swc_ephys/issues
Classifier: Development Status :: 2 - Pre-Alpha
Classifier: Programming Language :: Python
Classifier: Programming Language :: Python :: 3
Classifier: Programming Language :: Python :: 3.8
Classifier: Programming Language :: Python :: 3.9
Classifier: Programming Language :: Python :: 3.10
Classifier: Operating System :: OS Independent
Classifier: License :: OSI Approved :: BSD License
Requires-Python: >=3.8.0
License-File: LICENSE
Requires-Dist: spikeinterface (==0.98.2)
Requires-Dist: jax
Requires-Dist: jaxlib
Requires-Dist: spython
Requires-Dist: submitit
Requires-Dist: PyYAML
Requires-Dist: tridesclous
Requires-Dist: mountainsort5
Requires-Dist: docker
Provides-Extra: dev
Requires-Dist: pytest ; extra == 'dev'
Requires-Dist: pytest-cov ; extra == 'dev'
Requires-Dist: coverage ; extra == 'dev'
Requires-Dist: tox ; extra == 'dev'
Requires-Dist: black ; extra == 'dev'
Requires-Dist: mypy ; extra == 'dev'
Requires-Dist: pre-commit ; extra == 'dev'
Requires-Dist: ruff ; extra == 'dev'
Requires-Dist: setuptools-scm ; extra == 'dev'
Requires-Dist: types-PyYAML ; extra == 'dev'
